urlpattern/__init__.py
urlpattern/__init__.pyi
urlpattern/py.typed
urlpattern/urlpattern.cpython-311-x86_64-linux-gnu.so
urlpattern-0.1.8.dist-info/METADATA
urlpattern-0.1.8.dist-info/WHEEL
urlpattern-0.1.8.dist-info/licenses/LICENSE
urlpattern-0.1.8.dist-info/RECORD
