Metadata-Version: 2.4
Name: urlpattern
Version: 0.1.8
Classifier: Development Status :: 4 - Beta
Classifier: Intended Audience :: Developers
Classifier: License :: OSI Approved :: MIT License
Classifier: Operating System :: OS Independent
Classifier: Programming Language :: Python :: 3
Classifier: Programming Language :: Python :: 3 :: Only
Classifier: Programming Language :: Python :: 3.8
Classifier: Programming Language :: Python :: 3.9
Classifier: Programming Language :: Python :: 3.10
Classifier: Programming Language :: Python :: 3.11
Classifier: Programming Language :: Python :: 3.12
Classifier: Programming Language :: Python :: 3.13
Classifier: Programming Language :: Python :: 3.14
Classifier: Programming Language :: Python :: Free Threading
Classifier: Programming Language :: Python :: Implementation :: CPython
Classifier: Programming Language :: Python :: Implementation :: PyPy
Classifier: Programming Language :: Rust
Classifier: Topic :: Internet :: WWW/HTTP
Classifier: Typing :: Typed
License-File: LICENSE
Summary: An implementation of the URL Pattern Standard for Python written in Rust.
Keywords: urlpattern
Author-email: "방성범 (Bang Seongbeom)" <bangseongbeom@gmail.com>
Requires-Python: >=3.8
Project-URL: Homepage, https://github.com/urlpattern/python-urlpattern
Project-URL: Issues, https://github.com/urlpattern/python-urlpattern/issues
Project-URL: Repository, https://github.com/urlpattern/python-urlpattern.git
